formasaurus/__init__.py
formasaurus/__main__.py
formasaurus/annotation.py
formasaurus/classifiers.py
formasaurus/fieldtype_model.py
formasaurus/formhash.py
formasaurus/formtype_features.py
formasaurus/formtype_model.py
formasaurus/html.py
formasaurus/storage.py
formasaurus/text.py
formasaurus/utils.py
formasaurus/widgets.py
formasaurus/data/config.json
formasaurus/data/index.json
formasaurus/data/html/5kaixin.net-0.html
formasaurus/data/html/account.oneplus.net-0.html
formasaurus/data/html/account.swtor.com-0.html
formasaurus/data/html/account.swtor.com-1.html
formasaurus/data/html/allnokia.ru-0.html
formasaurus/data/html/apartments.camdenliving.com-0.html
formasaurus/data/html/app.cheezburger.com-0.html
formasaurus/data/html/app1.vocusgr.com-0.html
formasaurus/data/html/arijaycomet.com-0.html
formasaurus/data/html/arstechnica.com-0.html
formasaurus/data/html/ask.debian.net-0.html
formasaurus/data/html/asodao.info-0.html
formasaurus/data/html/asodao.info-1.html
formasaurus/data/html/astral-guild.net-0.html
formasaurus/data/html/auth.getpebble.com-0.html
formasaurus/data/html/auth.getpebble.com-1.html
formasaurus/data/html/auth.getpebble.com-2.html
formasaurus/data/html/auth.independent.ie-0.html
formasaurus/data/html/auth.independent.ie-1.html
formasaurus/data/html/belepes.t-online.hu-0.html
formasaurus/data/html/belepes.t-online.hu-1.html
formasaurus/data/html/berkeley.edu-0.html
formasaurus/data/html/berkeley.edu-1.html
formasaurus/data/html/binarymarket.ru-0.html
formasaurus/data/html/boston.custhelp.com-0.html
formasaurus/data/html/brookdalecc.instructure.com-0.html
formasaurus/data/html/brooklynbrewshop.com-0.html
formasaurus/data/html/brooklynbrewshop.com-1.html
formasaurus/data/html/brooklynbrewshop.com-2.html
formasaurus/data/html/brooklynbrewshop.com-3.html
formasaurus/data/html/brooklynbrewshop.com-4.html
formasaurus/data/html/brooklynbrewshop.com-5.html
formasaurus/data/html/brownpapertickets.com-0.html
formasaurus/data/html/buyee.jp-0.html
formasaurus-0.9.0.dist-info/METADATA
formasaurus-0.9.0.dist-info/WHEEL
formasaurus-0.9.0.dist-info/entry_points.txt
formasaurus-0.9.0.dist-info/top_level.txt
formasaurus-0.9.0.dist-info/RECORD
