Metadata-Version: 2.1
Name: formasaurus
Version: 0.9.0
Summary: Formasaurus tells you the types of HTML forms and their fields using machine learning
Home-page: https://github.com/scrapinghub/Formasaurus
Author: Mikhail Korobov
Author-email: kmike84@gmail.com
License: MIT license
Classifier: Development Status :: 4 - Beta
Classifier: License :: OSI Approved :: MIT License
Classifier: Intended Audience :: Developers
Classifier: Operating System :: OS Independent
Classifier: Programming Language :: Python
Classifier: Programming Language :: Python :: 3
Classifier: Programming Language :: Python :: 3.8
Classifier: Programming Language :: Python :: 3.9
Classifier: Programming Language :: Python :: 3.10
Classifier: Programming Language :: Python :: 3.11
Classifier: Programming Language :: Python :: 3.12
Requires-Dist: docopt >=0.4.0
Requires-Dist: requests >=1.0.0
Requires-Dist: tldextract >=1.2.0
Requires-Dist: tqdm >=2.0
Requires-Dist: w3lib >=1.13.0
Provides-Extra: annotation
Requires-Dist: ipython[notebook] >=4.0 ; extra == 'annotation'
Requires-Dist: ipywidgets ; extra == 'annotation'
Requires-Dist: Tornado >=4.0.0 ; extra == 'annotation'
Provides-Extra: with-deps
Requires-Dist: joblib >=1.2.0 ; extra == 'with-deps'
Requires-Dist: lxml >=4.4.1 ; extra == 'with-deps'
Requires-Dist: lxml-html-clean >=0.1.0 ; extra == 'with-deps'
Requires-Dist: scikit-learn >=0.24.0 ; extra == 'with-deps'
Requires-Dist: scipy >=1.5.1 ; extra == 'with-deps'
Requires-Dist: sklearn-crfsuite >=0.5.0 ; extra == 'with-deps'
Provides-Extra: with_deps
Requires-Dist: joblib >=1.2.0 ; extra == 'with_deps'
Requires-Dist: lxml >=4.4.1 ; extra == 'with_deps'
Requires-Dist: lxml-html-clean >=0.1.0 ; extra == 'with_deps'
Requires-Dist: scikit-learn >=0.24.0 ; extra == 'with_deps'
Requires-Dist: scipy >=1.5.1 ; extra == 'with_deps'
Requires-Dist: sklearn-crfsuite >=0.5.0 ; extra == 'with_deps'
